tap_totango/__init__.py
tap_totango/client.py
tap_totango/schemas/accounts.json
tap_totango/schemas/events.json
tap_totango/schemas/users.json
tap_totango/streams.py
tap_totango/tap.py
tap_totango-0.5.0.dist-info/METADATA
tap_totango-0.5.0.dist-info/WHEEL
tap_totango-0.5.0.dist-info/entry_points.txt
tap_totango-0.5.0.dist-info/RECORD
